[
  {
    "id": "mon-r1-1",
    "night": "monday",
    "division": "A",
    "round": 1,
    "date": "2026-03-23",
    "time": "19:00",
    "court": 1,
    "homeTeam": "mon-wildcats",
    "awayTeam": "mon-afg",
    "homeScore": 9,
    "awayScore": 7,
    "status": "completed"
  },
  {
    "id": "mon-r1-2",
    "night": "monday",
    "division": "A",
    "round": 1,
    "date": "2026-03-23",
    "time": "19:40",
    "court": 1,
    "homeTeam": "mon-goldlink-up",
    "awayTeam": "mon-blue-dragons",
    "homeScore": 9,
    "awayScore": 6,
    "status": "completed"
  },
  {
    "id": "mon-r1-3",
    "night": "monday",
    "division": "A",
    "round": 1,
    "date": "2026-03-23",
    "time": "19:40",
    "court": 2,
    "homeTeam": "mon-persepolis",
    "awayTeam": "mon-misfits",
    "homeScore": 5,
    "awayScore": 4,
    "status": "completed"
  },
  {
    "id": "mon-r1-4",
    "night": "monday",
    "division": "A",
    "round": 1,
    "date": "2026-03-23",
    "time": "20:20",
    "court": 1,
    "homeTeam": "mon-moza-mama",
    "awayTeam": "mon-samen",
    "homeScore": 5,
    "awayScore": 0,
    "status": "completed"
  },
  {
    "id": "mon-r2-1",
    "night": "monday",
    "division": "A",
    "round": 2,
    "date": "2026-03-30",
    "time": "19:00",
    "court": 1,
    "homeTeam": "mon-wildcats",
    "awayTeam": "mon-goldlink-up",
    "homeScore": 9,
    "awayScore": 6,
    "status": "completed"
  },
  {
    "id": "mon-r2-2",
    "night": "monday",
    "division": "A",
    "round": 2,
    "date": "2026-03-30",
    "time": "19:40",
    "court": 1,
    "homeTeam": "mon-persepolis",
    "awayTeam": "mon-moza-mama",
    "homeScore": 6,
    "awayScore": 5,
    "status": "completed"
  },
  {
    "id": "mon-r2-3",
    "night": "monday",
    "division": "A",
    "round": 2,
    "date": "2026-03-30",
    "time": "19:40",
    "court": 2,
    "homeTeam": "mon-misfits",
    "awayTeam": "mon-afg",
    "homeScore": 6,
    "awayScore": 8,
    "status": "completed"
  },
  {
    "id": "mon-r2-4",
    "night": "monday",
    "division": "A",
    "round": 2,
    "date": "2026-03-30",
    "time": "20:20",
    "court": 1,
    "homeTeam": "mon-samen",
    "awayTeam": "mon-blue-dragons",
    "homeScore": 15,
    "awayScore": 0,
    "status": "completed"
  },
  {
    "id": "mon-r3-1",
    "night": "monday",
    "division": "A",
    "round": 3,
    "date": "2026-04-13",
    "time": "19:00",
    "court": 1,
    "homeTeam": "mon-moza-mama",
    "awayTeam": "mon-goldlink-up",
    "homeScore": 6,
    "awayScore": 7,
    "status": "completed"
  },
  {
    "id": "mon-r3-2",
    "night": "monday",
    "division": "A",
    "round": 3,
    "date": "2026-04-13",
    "time": "19:40",
    "court": 1,
    "homeTeam": "mon-afg",
    "awayTeam": "mon-blue-dragons",
    "homeScore": 0,
    "awayScore": 5,
    "status": "completed"
  },
  {
    "id": "mon-r3-3",
    "night": "monday",
    "division": "A",
    "round": 3,
    "date": "2026-04-13",
    "time": "19:40",
    "court": 2,
    "homeTeam": "mon-misfits",
    "awayTeam": "mon-samen",
    "homeScore": 4,
    "awayScore": 5,
    "status": "completed"
  },
  {
    "id": "mon-r3-4",
    "night": "monday",
    "division": "A",
    "round": 3,
    "date": "2026-04-13",
    "time": "20:20",
    "court": 1,
    "homeTeam": "mon-persepolis",
    "awayTeam": "mon-wildcats",
    "homeScore": 6,
    "awayScore": 4,
    "status": "completed"
  },
  {
    "id": "mon-r4-1",
    "night": "monday",
    "division": "A",
    "round": 4,
    "date": "2026-04-20",
    "time": "19:00",
    "court": 1,
    "homeTeam": "mon-afg",
    "awayTeam": "mon-moza-mama",
    "homeScore": 9,
    "awayScore": 7,
    "status": "completed"
  },
  {
    "id": "mon-r4-2",
    "night": "monday",
    "division": "A",
    "round": 4,
    "date": "2026-04-20",
    "time": "19:40",
    "court": 1,
    "homeTeam": "mon-blue-dragons",
    "awayTeam": "mon-misfits",
    "homeScore": 0,
    "awayScore": 12,
    "status": "completed"
  },
  {
    "id": "mon-r4-3",
    "night": "monday",
    "division": "A",
    "round": 4,
    "date": "2026-04-20",
    "time": "19:40",
    "court": 2,
    "homeTeam": "mon-goldlink-up",
    "awayTeam": "mon-persepolis",
    "homeScore": 6,
    "awayScore": 6,
    "status": "completed"
  },
  {
    "id": "mon-r4-4",
    "night": "monday",
    "division": "A",
    "round": 4,
    "date": "2026-04-20",
    "time": "20:20",
    "court": 1,
    "homeTeam": "mon-wildcats",
    "awayTeam": "mon-samen",
    "homeScore": 4,
    "awayScore": 1,
    "status": "completed"
  },
  {
    "id": "mon-r4-5",
    "night": "monday",
    "division": "A",
    "round": 4,
    "date": "2026-04-20",
    "time": "20:20",
    "court": 2,
    "homeTeam": "mon-buckle-city",
    "awayTeam": "mon-tolaka-group",
    "homeScore": 7,
    "awayScore": 6,
    "status": "completed"
  },
  {
    "id": "mon-r5-1",
    "night": "monday",
    "division": "A",
    "round": 5,
    "date": "2026-04-27",
    "time": "19:00",
    "court": 1,
    "homeTeam": "mon-afg",
    "awayTeam": "mon-persepolis",
    "homeScore": 1,
    "awayScore": 3,
    "status": "completed"
  },
  {
    "id": "mon-r5-2",
    "night": "monday",
    "division": "A",
    "round": 5,
    "date": "2026-04-27",
    "time": "19:40",
    "court": 1,
    "homeTeam": "mon-buckle-city",
    "awayTeam": "mon-blue-dragons",
    "homeScore": 2,
    "awayScore": 4,
    "status": "completed"
  },
  {
    "id": "mon-r5-3",
    "night": "monday",
    "division": "A",
    "round": 5,
    "date": "2026-04-27",
    "time": "19:00",
    "court": 2,
    "homeTeam": "mon-wildcats",
    "awayTeam": "mon-misfits",
    "homeScore": 4,
    "awayScore": 5,
    "status": "completed"
  },
  {
    "id": "mon-r5-4",
    "night": "monday",
    "division": "A",
    "round": 5,
    "date": "2026-04-27",
    "time": "20:20",
    "court": 1,
    "homeTeam": "mon-goldlink-up",
    "awayTeam": "mon-samen",
    "homeScore": 4,
    "awayScore": 7,
    "status": "completed"
  },
  {
    "id": "mon-r5-5",
    "night": "monday",
    "division": "A",
    "round": 5,
    "date": "2026-04-27",
    "time": "20:20",
    "court": 2,
    "homeTeam": "mon-tolaka-group",
    "awayTeam": "mon-moza-mama",
    "homeScore": 8,
    "awayScore": 6,
    "status": "completed"
  },
  {
    "id": "mon-r6-1",
    "night": "monday",
    "division": "A",
    "round": 6,
    "date": "2026-05-04",
    "time": "19:00",
    "court": 1,
    "homeTeam": "mon-afg",
    "awayTeam": "mon-samen",
    "status": "scheduled"
  },
  {
    "id": "mon-r6-2",
    "night": "monday",
    "division": "A",
    "round": 6,
    "date": "2026-05-04",
    "time": "19:40",
    "court": 1,
    "homeTeam": "mon-blue-dragons",
    "awayTeam": "mon-persepolis",
    "status": "scheduled"
  },
  {
    "id": "mon-r6-3",
    "night": "monday",
    "division": "A",
    "round": 6,
    "date": "2026-05-04",
    "time": "19:40",
    "court": 2,
    "homeTeam": "mon-buckle-city",
    "awayTeam": "mon-wildcats",
    "status": "scheduled"
  },
  {
    "id": "mon-r6-4",
    "night": "monday",
    "division": "A",
    "round": 6,
    "date": "2026-05-04",
    "time": "20:20",
    "court": 1,
    "homeTeam": "mon-goldlink-up",
    "awayTeam": "mon-tolaka-group",
    "status": "scheduled"
  },
  {
    "id": "mon-r6-5",
    "night": "monday",
    "division": "A",
    "round": 6,
    "date": "2026-05-04",
    "time": "20:20",
    "court": 2,
    "homeTeam": "mon-misfits",
    "awayTeam": "mon-moza-mama",
    "status": "scheduled"
  },
  {
    "id": "mon-r7-1",
    "night": "monday",
    "division": "A",
    "round": 7,
    "date": "2026-05-11",
    "time": "19:00",
    "court": 1,
    "homeTeam": "mon-afg",
    "awayTeam": "mon-misfits",
    "status": "scheduled"
  },
  {
    "id": "mon-r7-2",
    "night": "monday",
    "division": "A",
    "round": 7,
    "date": "2026-05-11",
    "time": "19:40",
    "court": 1,
    "homeTeam": "mon-blue-dragons",
    "awayTeam": "mon-goldlink-up",
    "status": "scheduled"
  },
  {
    "id": "mon-r7-3",
    "night": "monday",
    "division": "A",
    "round": 7,
    "date": "2026-05-11",
    "time": "20:20",
    "court": 1,
    "homeTeam": "mon-moza-mama",
    "awayTeam": "mon-buckle-city",
    "status": "scheduled"
  },
  {
    "id": "mon-r7-4",
    "night": "monday",
    "division": "A",
    "round": 7,
    "date": "2026-05-11",
    "time": "19:40",
    "court": 2,
    "homeTeam": "mon-samen",
    "awayTeam": "mon-persepolis",
    "status": "scheduled"
  },
  {
    "id": "mon-r7-5",
    "night": "monday",
    "division": "A",
    "round": 7,
    "date": "2026-05-11",
    "time": "20:20",
    "court": 2,
    "homeTeam": "mon-wildcats",
    "awayTeam": "mon-tolaka-group",
    "status": "scheduled"
  },
  {
    "id": "mon-r8-1",
    "night": "monday",
    "division": "A",
    "round": 8,
    "date": "2026-05-18",
    "time": "19:00",
    "court": 1,
    "homeTeam": "mon-afg",
    "awayTeam": "mon-buckle-city",
    "status": "scheduled"
  },
  {
    "id": "mon-r8-2",
    "night": "monday",
    "division": "A",
    "round": 8,
    "date": "2026-05-18",
    "time": "19:40",
    "court": 1,
    "homeTeam": "mon-blue-dragons",
    "awayTeam": "mon-wildcats",
    "status": "scheduled"
  },
  {
    "id": "mon-r8-3",
    "night": "monday",
    "division": "A",
    "round": 8,
    "date": "2026-05-18",
    "time": "19:40",
    "court": 2,
    "homeTeam": "mon-goldlink-up",
    "awayTeam": "mon-samen",
    "status": "scheduled"
  },
  {
    "id": "mon-r8-4",
    "night": "monday",
    "division": "A",
    "round": 8,
    "date": "2026-05-18",
    "time": "20:20",
    "court": 1,
    "homeTeam": "mon-misfits",
    "awayTeam": "mon-tolaka-group",
    "status": "scheduled"
  },
  {
    "id": "mon-r8-5",
    "night": "monday",
    "division": "A",
    "round": 8,
    "date": "2026-05-18",
    "time": "20:20",
    "court": 2,
    "homeTeam": "mon-moza-mama",
    "awayTeam": "mon-persepolis",
    "status": "scheduled"
  },
  {
    "id": "mon-r9-1",
    "night": "monday",
    "division": "A",
    "round": 9,
    "date": "2026-05-25",
    "time": "19:00",
    "court": 1,
    "homeTeam": "mon-goldlink-up",
    "awayTeam": "mon-afg",
    "status": "scheduled"
  },
  {
    "id": "mon-r9-2",
    "night": "monday",
    "division": "A",
    "round": 9,
    "date": "2026-05-25",
    "time": "19:40",
    "court": 1,
    "homeTeam": "mon-moza-mama",
    "awayTeam": "mon-blue-dragons",
    "status": "scheduled"
  },
  {
    "id": "mon-r9-3",
    "night": "monday",
    "division": "A",
    "round": 9,
    "date": "2026-05-25",
    "time": "19:40",
    "court": 2,
    "homeTeam": "mon-samen",
    "awayTeam": "mon-buckle-city",
    "status": "scheduled"
  },
  {
    "id": "mon-r9-4",
    "night": "monday",
    "division": "A",
    "round": 9,
    "date": "2026-05-25",
    "time": "20:20",
    "court": 1,
    "homeTeam": "mon-wildcats",
    "awayTeam": "mon-misfits",
    "status": "scheduled"
  },
  {
    "id": "mon-r9-5",
    "night": "monday",
    "division": "A",
    "round": 9,
    "date": "2026-05-25",
    "time": "20:20",
    "court": 2,
    "homeTeam": "mon-tolaka-group",
    "awayTeam": "mon-persepolis",
    "status": "scheduled"
  },
  {
    "id": "mon-r10-1",
    "night": "monday",
    "division": "A",
    "round": 10,
    "date": "2026-06-01",
    "time": "19:00",
    "court": 1,
    "homeTeam": "mon-moza-mama",
    "awayTeam": "mon-afg",
    "status": "scheduled"
  },
  {
    "id": "mon-r10-2",
    "night": "monday",
    "division": "A",
    "round": 10,
    "date": "2026-06-01",
    "time": "20:20",
    "court": 1,
    "homeTeam": "mon-blue-dragons",
    "awayTeam": "mon-buckle-city",
    "status": "scheduled"
  },
  {
    "id": "mon-r10-3",
    "night": "monday",
    "division": "A",
    "round": 10,
    "date": "2026-06-01",
    "time": "19:40",
    "court": 2,
    "homeTeam": "mon-persepolis",
    "awayTeam": "mon-goldlink-up",
    "status": "scheduled"
  },
  {
    "id": "mon-r10-4",
    "night": "monday",
    "division": "A",
    "round": 10,
    "date": "2026-06-01",
    "time": "19:40",
    "court": 1,
    "homeTeam": "mon-tolaka-group",
    "awayTeam": "mon-misfits",
    "status": "scheduled"
  },
  {
    "id": "mon-r10-5",
    "night": "monday",
    "division": "A",
    "round": 10,
    "date": "2026-06-01",
    "time": "20:20",
    "court": 2,
    "homeTeam": "mon-samen",
    "awayTeam": "mon-wildcats",
    "status": "scheduled"
  },
  {
    "id": "mon-r11-1",
    "night": "monday",
    "division": "A",
    "round": 11,
    "date": "2026-06-15",
    "time": "19:00",
    "court": 1,
    "homeTeam": "mon-tolaka-group",
    "awayTeam": "mon-afg",
    "status": "scheduled"
  },
  {
    "id": "mon-r11-2",
    "night": "monday",
    "division": "A",
    "round": 11,
    "date": "2026-06-15",
    "time": "19:40",
    "court": 1,
    "homeTeam": "mon-wildcats",
    "awayTeam": "mon-blue-dragons",
    "status": "scheduled"
  },
  {
    "id": "mon-r11-3",
    "night": "monday",
    "division": "A",
    "round": 11,
    "date": "2026-06-15",
    "time": "19:40",
    "court": 2,
    "homeTeam": "mon-goldlink-up",
    "awayTeam": "mon-buckle-city",
    "status": "scheduled"
  },
  {
    "id": "mon-r11-4",
    "night": "monday",
    "division": "A",
    "round": 11,
    "date": "2026-06-15",
    "time": "20:20",
    "court": 1,
    "homeTeam": "mon-samen",
    "awayTeam": "mon-misfits",
    "status": "scheduled"
  },
  {
    "id": "mon-r11-5",
    "night": "monday",
    "division": "A",
    "round": 11,
    "date": "2026-06-15",
    "time": "20:20",
    "court": 2,
    "homeTeam": "mon-persepolis",
    "awayTeam": "mon-moza-mama",
    "status": "scheduled"
  },
  {
    "id": "mon-r12-1",
    "night": "monday",
    "division": "A",
    "round": 12,
    "date": "2026-06-22",
    "time": "19:00",
    "court": 1,
    "homeTeam": "mon-afg",
    "awayTeam": "mon-persepolis",
    "status": "scheduled"
  },
  {
    "id": "mon-r12-2",
    "night": "monday",
    "division": "A",
    "round": 12,
    "date": "2026-06-22",
    "time": "19:40",
    "court": 1,
    "homeTeam": "mon-blue-dragons",
    "awayTeam": "mon-samen",
    "status": "scheduled"
  },
  {
    "id": "mon-r12-3",
    "night": "monday",
    "division": "A",
    "round": 12,
    "date": "2026-06-22",
    "time": "19:40",
    "court": 2,
    "homeTeam": "mon-buckle-city",
    "awayTeam": "mon-misfits",
    "status": "scheduled"
  },
  {
    "id": "mon-r12-4",
    "night": "monday",
    "division": "A",
    "round": 12,
    "date": "2026-06-22",
    "time": "20:20",
    "court": 1,
    "homeTeam": "mon-goldlink-up",
    "awayTeam": "mon-moza-mama",
    "status": "scheduled"
  },
  {
    "id": "mon-r12-5",
    "night": "monday",
    "division": "A",
    "round": 12,
    "date": "2026-06-22",
    "time": "20:20",
    "court": 2,
    "homeTeam": "mon-tolaka-group",
    "awayTeam": "mon-wildcats",
    "status": "scheduled"
  },
  {
    "id": "mon-r13-1",
    "night": "monday",
    "division": "A",
    "round": 13,
    "date": "2026-06-29",
    "time": "19:00",
    "court": 1,
    "homeTeam": "mon-misfits",
    "awayTeam": "mon-buckle-city",
    "status": "scheduled"
  },
  {
    "id": "mon-r13-2",
    "night": "monday",
    "division": "A",
    "round": 13,
    "date": "2026-06-29",
    "time": "19:40",
    "court": 1,
    "homeTeam": "mon-blue-dragons",
    "awayTeam": "mon-afg",
    "status": "scheduled"
  },
  {
    "id": "mon-r13-3",
    "night": "monday",
    "division": "A",
    "round": 13,
    "date": "2026-06-29",
    "time": "19:40",
    "court": 2,
    "homeTeam": "mon-goldlink-up",
    "awayTeam": "mon-wildcats",
    "status": "scheduled"
  },
  {
    "id": "mon-r13-4",
    "night": "monday",
    "division": "A",
    "round": 13,
    "date": "2026-06-29",
    "time": "20:20",
    "court": 1,
    "homeTeam": "mon-samen",
    "awayTeam": "mon-moza-mama",
    "status": "scheduled"
  },
  {
    "id": "mon-r13-5",
    "night": "monday",
    "division": "A",
    "round": 13,
    "date": "2026-06-29",
    "time": "20:20",
    "court": 2,
    "homeTeam": "mon-persepolis",
    "awayTeam": "mon-tolaka-group",
    "status": "scheduled"
  },
  {
    "id": "mon-r14-1",
    "night": "monday",
    "division": "A",
    "round": 14,
    "date": "2026-07-06",
    "time": "19:00",
    "court": 1,
    "homeTeam": "mon-afg",
    "awayTeam": "mon-tolaka-group",
    "status": "scheduled"
  },
  {
    "id": "mon-r14-2",
    "night": "monday",
    "division": "A",
    "round": 14,
    "date": "2026-07-06",
    "time": "19:40",
    "court": 1,
    "homeTeam": "mon-persepolis",
    "awayTeam": "mon-blue-dragons",
    "status": "scheduled"
  },
  {
    "id": "mon-r14-3",
    "night": "monday",
    "division": "A",
    "round": 14,
    "date": "2026-07-06",
    "time": "19:40",
    "court": 2,
    "homeTeam": "mon-buckle-city",
    "awayTeam": "mon-samen",
    "status": "scheduled"
  },
  {
    "id": "mon-r14-4",
    "night": "monday",
    "division": "A",
    "round": 14,
    "date": "2026-07-06",
    "time": "20:20",
    "court": 1,
    "homeTeam": "mon-goldlink-up",
    "awayTeam": "mon-misfits",
    "status": "scheduled"
  },
  {
    "id": "mon-r14-5",
    "night": "monday",
    "division": "A",
    "round": 14,
    "date": "2026-07-06",
    "time": "20:20",
    "court": 2,
    "homeTeam": "mon-moza-mama",
    "awayTeam": "mon-wildcats",
    "status": "scheduled"
  },
  {
    "id": "mon-r15-1",
    "night": "monday",
    "division": "A",
    "round": 15,
    "date": "2026-07-13",
    "time": "19:00",
    "court": 1,
    "homeTeam": "mon-samen",
    "awayTeam": "mon-afg",
    "status": "scheduled"
  },
  {
    "id": "mon-r15-2",
    "night": "monday",
    "division": "A",
    "round": 15,
    "date": "2026-07-13",
    "time": "19:40",
    "court": 1,
    "homeTeam": "mon-goldlink-up",
    "awayTeam": "mon-blue-dragons",
    "status": "scheduled"
  },
  {
    "id": "mon-r15-3",
    "night": "monday",
    "division": "A",
    "round": 15,
    "date": "2026-07-13",
    "time": "20:20",
    "court": 1,
    "homeTeam": "mon-wildcats",
    "awayTeam": "mon-buckle-city",
    "status": "scheduled"
  },
  {
    "id": "mon-r15-4",
    "night": "monday",
    "division": "A",
    "round": 15,
    "date": "2026-07-13",
    "time": "19:40",
    "court": 2,
    "homeTeam": "mon-misfits",
    "awayTeam": "mon-persepolis",
    "status": "scheduled"
  },
  {
    "id": "mon-r15-5",
    "night": "monday",
    "division": "A",
    "round": 15,
    "date": "2026-07-13",
    "time": "20:20",
    "court": 2,
    "homeTeam": "mon-tolaka-group",
    "awayTeam": "mon-moza-mama",
    "status": "scheduled"
  },
  {
    "id": "mon-r16-1",
    "night": "monday",
    "division": "A",
    "round": 16,
    "date": "2026-07-20",
    "time": "19:00",
    "court": 1,
    "homeTeam": "mon-afg",
    "awayTeam": "mon-goldlink-up",
    "status": "scheduled"
  },
  {
    "id": "mon-r16-2",
    "night": "monday",
    "division": "A",
    "round": 16,
    "date": "2026-07-20",
    "time": "19:40",
    "court": 1,
    "homeTeam": "mon-blue-dragons",
    "awayTeam": "mon-moza-mama",
    "status": "scheduled"
  },
  {
    "id": "mon-r16-3",
    "night": "monday",
    "division": "A",
    "round": 16,
    "date": "2026-07-20",
    "time": "19:40",
    "court": 2,
    "homeTeam": "mon-buckle-city",
    "awayTeam": "mon-persepolis",
    "status": "scheduled"
  },
  {
    "id": "mon-r16-4",
    "night": "monday",
    "division": "A",
    "round": 16,
    "date": "2026-07-20",
    "time": "20:20",
    "court": 1,
    "homeTeam": "mon-misfits",
    "awayTeam": "mon-wildcats",
    "status": "scheduled"
  },
  {
    "id": "mon-r16-5",
    "night": "monday",
    "division": "A",
    "round": 16,
    "date": "2026-07-20",
    "time": "20:20",
    "court": 2,
    "homeTeam": "mon-samen",
    "awayTeam": "mon-tolaka-group",
    "status": "scheduled"
  },
  {
    "id": "mon-r17-1",
    "night": "monday",
    "division": "A",
    "round": 17,
    "date": "2026-07-27",
    "time": "19:00",
    "court": 1,
    "homeTeam": "mon-buckle-city",
    "awayTeam": "mon-afg",
    "status": "scheduled"
  },
  {
    "id": "mon-r17-2",
    "night": "monday",
    "division": "A",
    "round": 17,
    "date": "2026-07-27",
    "time": "19:40",
    "court": 1,
    "homeTeam": "mon-tolaka-group",
    "awayTeam": "mon-blue-dragons",
    "status": "scheduled"
  },
  {
    "id": "mon-r17-3",
    "night": "monday",
    "division": "A",
    "round": 17,
    "date": "2026-07-27",
    "time": "19:40",
    "court": 2,
    "homeTeam": "mon-samen",
    "awayTeam": "mon-goldlink-up",
    "status": "scheduled"
  },
  {
    "id": "mon-r17-4",
    "night": "monday",
    "division": "A",
    "round": 17,
    "date": "2026-07-27",
    "time": "20:20",
    "court": 1,
    "homeTeam": "mon-moza-mama",
    "awayTeam": "mon-misfits",
    "status": "scheduled"
  },
  {
    "id": "mon-r17-5",
    "night": "monday",
    "division": "A",
    "round": 17,
    "date": "2026-07-27",
    "time": "20:20",
    "court": 2,
    "homeTeam": "mon-wildcats",
    "awayTeam": "mon-persepolis",
    "status": "scheduled"
  },
  {
    "id": "mon-r18-1",
    "night": "monday",
    "division": "A",
    "round": 18,
    "date": "2026-08-03",
    "time": "19:00",
    "court": 1,
    "homeTeam": "mon-afg",
    "awayTeam": "mon-wildcats",
    "status": "scheduled"
  },
  {
    "id": "mon-r18-2",
    "night": "monday",
    "division": "A",
    "round": 18,
    "date": "2026-08-03",
    "time": "19:40",
    "court": 1,
    "homeTeam": "mon-misfits",
    "awayTeam": "mon-blue-dragons",
    "status": "scheduled"
  },
  {
    "id": "mon-r18-3",
    "night": "monday",
    "division": "A",
    "round": 18,
    "date": "2026-08-03",
    "time": "19:40",
    "court": 2,
    "homeTeam": "mon-buckle-city",
    "awayTeam": "mon-moza-mama",
    "status": "scheduled"
  },
  {
    "id": "mon-r18-4",
    "night": "monday",
    "division": "A",
    "round": 18,
    "date": "2026-08-03",
    "time": "20:20",
    "court": 1,
    "homeTeam": "mon-tolaka-group",
    "awayTeam": "mon-goldlink-up",
    "status": "scheduled"
  },
  {
    "id": "mon-r18-5",
    "night": "monday",
    "division": "A",
    "round": 18,
    "date": "2026-08-03",
    "time": "20:20",
    "court": 2,
    "homeTeam": "mon-persepolis",
    "awayTeam": "mon-samen",
    "status": "scheduled"
  }
]
